docop_tasks/__init__.py
docop_tasks/webhtml/__init__.py
docop_tasks/webhtml/fetch_html.py
docop_tasks-0.3.4.dist-info/LICENSE
docop_tasks-0.3.4.dist-info/METADATA
docop_tasks-0.3.4.dist-info/WHEEL
docop_tasks-0.3.4.dist-info/entry_points.txt
docop_tasks-0.3.4.dist-info/top_level.txt
docop_tasks-0.3.4.dist-info/RECORD
